lektor_s3.py
lektor_s3-0.5.1.dist-info/METADATA
lektor_s3-0.5.1.dist-info/RECORD
lektor_s3-0.5.1.dist-info/WHEEL
lektor_s3-0.5.1.dist-info/entry_points.txt
lektor_s3-0.5.1.dist-info/top_level.txt
