Metadata-Version: 2.1
Name: lektor-s3
Version: 0.5.1
Summary: Lektor plugin to support publishing to S3
Home-page: https://github.com/spenczar/lektor-s3
Author: Spencer Nelson
Author-email: s@spenczar.com
License: MIT
Platform: any
Classifier: Development Status :: 4 - Beta
Classifier: Environment :: Plugins
Classifier: Environment :: Web Environment
Classifier: Framework :: Lektor
Classifier: Intended Audience :: Developers
Classifier: License :: OSI Approved :: MIT License
Classifier: Operating System :: OS Independent
Classifier: Programming Language :: Python :: 2.7
Classifier: Topic :: Internet :: WWW/HTTP :: Site Management
Classifier: Topic :: Software Development :: Libraries :: Python Modules
Requires-Dist: Lektor
Requires-Dist: boto3 (>=1.1.4)
Requires-Dist: s3transfer
Requires-Dist: inifile
